proteo_suite/__init__.py
proteo_suite/analysis.py
proteo_suite/pipeline.py
proteo_suite/validation.py
proteo_suite_json9112-0.1.16.dist-info/METADATA
proteo_suite_json9112-0.1.16.dist-info/WHEEL
proteo_suite_json9112-0.1.16.dist-info/top_level.txt
proteo_suite_json9112-0.1.16.dist-info/RECORD
