Metadata-Version: 2.4
Name: proteo-suite-json9112
Version: 0.1.16
Summary: Advanced Proteomics Analysis Suite for Medical Outcomes Prediction
Author-email: json9112 <json9112@example.com>
Project-URL: Homepage, https://github.com/tablettab/proteo_suite
Classifier: Programming Language :: Python :: 3
Classifier: License :: OSI Approved :: MIT License
Classifier: Operating System :: OS Independent
Requires-Python: >=3.8
Requires-Dist: numpy
Requires-Dist: pandas
Requires-Dist: scikit-learn
Requires-Dist: scipy
Requires-Dist: matplotlib
Requires-Dist: seaborn
Requires-Dist: xgboost
Requires-Dist: lightgbm
Requires-Dist: catboost
Requires-Dist: lifelines
Requires-Dist: torch
Requires-Dist: umap-learn
